{
  "name": "widget",
  "version": "2.7",
  "description": {
    "en": "Widget",
    "ru": "Widget",
    "uk": "Widget"
  },
  "url": "https://github.com/pytsite/plugin-widget",
  "author": {
    "name": "Alexander Shepetko",
    "email": "a@shepetko.com",
    "url": "https://shepetko.com"
  },
  "requires": {
    "pytsite": ">=7.28",
    "plugins": [
      "assetman",
      "font_awesome",
      "hreflang",
      "jquery",
      "jquery_ui",
      "jquery_colorpicker",
      "jquery_datetimepicker>=1.2",
      "jquery_inputmask>=1.2",
      "js_select2",
      "js_typeahead",
      "twitter_bootstrap_table",
      "twitter_bootstrap_tokenfield"
    ]
  }
}
